semantic_components/__init__.py
semantic_components/cluster_pipeline.py
semantic_components/decomposition.py
semantic_components/evaluation.py
semantic_components/representation.py
semantic_components/sca.py
semantic_components/translate_gpt.py
semantic_components-0.1.1.dist-info/LICENSE
semantic_components-0.1.1.dist-info/METADATA
semantic_components-0.1.1.dist-info/WHEEL
semantic_components-0.1.1.dist-info/top_level.txt
semantic_components-0.1.1.dist-info/RECORD
