Metadata-Version: 2.1
Name: semantic_components
Version: 0.1.1
Summary: Finding semantic components in your neural representations.
Author-email: Florian Eichin <feichin@cis.lmu.de>
License: MIT License
Project-URL: Documentation, https://github.com/mainlp/semantic_components
Project-URL: Homepage, https://github.com/mainlp/semantic_components
Project-URL: Issues, https://github.com/mainlp/semantic_components/issues
Project-URL: Repository, https://github.com/mainlp/semantic_components
Keywords: nlp,clustering,topic,modeling,embeddings
Classifier: Intended Audience :: Developers
Classifier: Intended Audience :: Science/Research
Classifier: License :: OSI Approved :: MIT License
Classifier: Operating System :: MacOS
Classifier: Operating System :: Microsoft :: Windows
Classifier: Operating System :: POSIX
Classifier: Operating System :: Unix
Classifier: Programming Language :: Python
Classifier: Programming Language :: Python :: 3.8
Classifier: Programming Language :: Python :: 3.9
Classifier: Programming Language :: Python :: 3.10
Classifier: Programming Language :: Python :: 3.11
Classifier: Programming Language :: Python :: 3.12
Classifier: Topic :: Scientific/Engineering
Classifier: Topic :: Scientific/Engineering :: Artificial Intelligence
Requires-Python: >=3.8
License-File: LICENSE
Requires-Dist: numpy >=1.26.4
Requires-Dist: hdbscan >=0.8.39
Requires-Dist: jieba >=0.42.1
Requires-Dist: pandas >=2.2.3
Requires-Dist: scikit-learn >=1.1.0
Requires-Dist: sentence-transformers >=3.2.0
Requires-Dist: torch >=2.4.1
Requires-Dist: transformers >=4.45.2
Requires-Dist: umap-learn >=0.5.6
Provides-Extra: octis
Requires-Dist: numpy ==1.26.4 ; extra == 'octis'
Requires-Dist: scikit-learn ==1.1.0 ; extra == 'octis'
Requires-Dist: octis >=1.14.0 ; extra == 'octis'
